<annotation>
	<folder>all_imgs</folder>
	<filename>IMG_20230520_150312.jpg</filename>
	<path>D:\SSD_MobileNet_Skripsi\Tensorflow\workspace\images\all_imgs\IMG_20230520_150312.jpg</path>
	<source>
		<database>Unknown</database>
	</source>
	<size>
		<width>3000</width>
		<height>4000</height>
		<depth>3</depth>
	</size>
	<segmented>0</segmented>
	<object>
		<name>Gelas CW</name>
		<pose>Unspecified</pose>
		<truncated>0</truncated>
		<difficult>0</difficult>
		<bndbox>
			<xmin>619</xmin>
			<ymin>1527</ymin>
			<xmax>1240</xmax>
			<ymax>2483</ymax>
		</bndbox>
	</object>
</annotation>
